[{"place_id": 194750329, "licence": "Data \u00a9 OpenStreetMap contributors, ODbL 1.0. http://osm.org/copyright", "osm_type": "node", "osm_id": 10655209942, "lat": "37.5849720", "lon": "36.9310985", "class": "place", "type": "suburb", "place_rank": 19, "importance": 0.14672777065690085, "addresstype": "suburb", "name": "Turan", "display_name": "Turan, Kahramanmara\u015f, Dulkadiro\u011flu, Kahramanmara\u015f, Mediterranean Region, 36002, Turkey", "boundingbox": ["37.5649720", "37.6049720", "36.9110985", "36.9510985"], "geojson": {"type": "Point", "coordinates": [36.9310985, 37.584972]}}]