[{"place_id": 192813365, "licence": "Data \u00a9 OpenStreetMap contributors, ODbL 1.0. http://osm.org/copyright", "osm_type": "node", "osm_id": 8121967091, "lat": "37.0858556", "lon": "40.4923415", "class": "place", "type": "village", "place_rank": 19, "importance": 0.3797855310791376, "addresstype": "village", "name": "Ortak\u00f6y", "display_name": "Ortak\u00f6y, K\u0131z\u0131ltepe, Mardin, Southeastern Anatolia Region, Turkey", "boundingbox": ["37.0658556", "37.1058556", "40.4723415", "40.5123415"], "geojson": {"type": "Point", "coordinates": [40.4923415, 37.0858556]}}]